py_hd_wallet/__init__.py
py_hd_wallet/mw.py
py_hd_wallet/ripple.py
py_hd_wallet/wallet.py
py_hdwallet/__init__.py
py_hdwallet/mw.py
py_hdwallet/ripple.py
py_hdwallet/wallet.py
py_hd_wallet-0.1.dist-info/LICENCE.txt
py_hd_wallet-0.1.dist-info/METADATA
py_hd_wallet-0.1.dist-info/WHEEL
py_hd_wallet-0.1.dist-info/top_level.txt
py_hd_wallet-0.1.dist-info/RECORD
