Metadata-Version: 2.1
Name: py-hd-wallet
Version: 0.1
Summary: A multi-cryptocurrency HD wallet implemented by Python
Home-page: https://github.com/nthtson/py_hd_wallet
Author: Nguyen Tran Ho Thanh Son
Author-email: nguyentranhothanhson@gmail.com
License: LICENSE.txt
Platform: UNKNOWN
Requires-Dist: pywallet (==0.1.0)
Requires-Dist: pycoin (==0.80)
Requires-Dist: mnemonic (==0.18)
Requires-Dist: pysha3 (==1.0.2)
Requires-Dist: pycryptodome (==3.8.2)
Requires-Dist: hashprint (==1.0.1)
Requires-Dist: seed-phrases-for-stellar (==0.2)
Requires-Dist: toml (==0.10.0)
